pyscada/__init__.py
pyscada/onewire/__init__.py
pyscada/onewire/admin.py
pyscada/onewire/apps.py
pyscada/onewire/device.py
pyscada/onewire/models.py
pyscada/onewire/signals.py
pyscada/onewire/worker.py
pyscada/onewire/migrations/0001_initial.py
pyscada/onewire/migrations/0002_auto_20170225_0907.py
pyscada/onewire/migrations/0003_onewiredevice.py
pyscada/onewire/migrations/0004_auto_20170405_1750.py
pyscada/onewire/migrations/0005_extendedonewiredevice_extendedonewirevariable.py
pyscada/onewire/migrations/0006_auto_20210601_1443.py
pyscada/onewire/migrations/0007_auto_20210601_1445.py
pyscada/onewire/migrations/0008_add_device_protocol.py
pyscada/onewire/migrations/__init__.py
pyscada_onewire-0.8.0.dist-info/AUTHORS
pyscada_onewire-0.8.0.dist-info/LICENSE
pyscada_onewire-0.8.0.dist-info/METADATA
pyscada_onewire-0.8.0.dist-info/WHEEL
pyscada_onewire-0.8.0.dist-info/top_level.txt
pyscada_onewire-0.8.0.dist-info/RECORD
